escam_sliceselector/__init__.py
escam_sliceselector/background.py
escam_sliceselector/sliceselector.py
escam_sliceselector-1.0.10.dist-info/AUTHORS.rst
escam_sliceselector-1.0.10.dist-info/LICENSE
escam_sliceselector-1.0.10.dist-info/METADATA
escam_sliceselector-1.0.10.dist-info/WHEEL
escam_sliceselector-1.0.10.dist-info/entry_points.txt
escam_sliceselector-1.0.10.dist-info/top_level.txt
escam_sliceselector-1.0.10.dist-info/RECORD
